mlso/api/__init__.py
mlso/api/client.py
mlso_api_client-0.4.0.dist-info/licenses/LICENSE
mlso_api_client-0.4.0.dist-info/METADATA
mlso_api_client-0.4.0.dist-info/WHEEL
mlso_api_client-0.4.0.dist-info/entry_points.txt
mlso_api_client-0.4.0.dist-info/top_level.txt
mlso_api_client-0.4.0.dist-info/RECORD
