Metadata-Version: 2.4
Name: mlso-api-client
Version: 0.4.0
Summary: Python package providing a client to access Mauna Loa Solar Observatory (MLSO) data
Author: Michael Galloy
Author-email: Michael Galloy <mgalloy@ucar.edu>
License-Expression: MIT
Project-URL: homepage, https://www2.hao.ucar.edu/mlso
Project-URL: repository, https://github.com/NCAR/mlso-api-client
Project-URL: documentation, https://mlso-api-client.readthedocs.io/en/latest/
Project-URL: issues, https://github.com/NCAR/mlso-api-client/issues
Project-URL: changelog, https://github.com/NCAR/mlso-api-client/blob/master/CHANGELOG.md
Keywords: webservice,Mauna Loa Solar Observatory,MLSO,solar
Classifier: Development Status :: 4 - Beta
Classifier: Intended Audience :: Developers
Classifier: Intended Audience :: Science/Research
Classifier: Natural Language :: English
Classifier: Programming Language :: Python
Requires-Python: >=3.9
License-File: LICENSE
Requires-Dist: requests
Requires-Dist: tqdm
Provides-Extra: dev
Requires-Dist: pytest; extra == "dev"
Requires-Dist: pytest-cov; extra == "dev"
Requires-Dist: pre-commit; extra == "dev"
Requires-Dist: tox; extra == "dev"
Requires-Dist: wheel; extra == "dev"
Requires-Dist: watchdog; extra == "dev"
Requires-Dist: Sphinx; extra == "dev"
Requires-Dist: twine; extra == "dev"
Requires-Dist: coverage; extra == "dev"
Requires-Dist: flake8; extra == "dev"
Requires-Dist: pytest-runner; extra == "dev"
Requires-Dist: black; extra == "dev"
Requires-Dist: sphinx_rtd_theme; extra == "dev"
Requires-Dist: myst-parser; extra == "dev"
Dynamic: license-file
